parac/__init__.py
parac/const.py
parac/exceptions.py
parac/logging.py
parac/abc/__init__.py
parac/abc/base_ctx.py
parac/abc/base_error_handler.py
parac/abc/base_stream.py
parac/abc/base_tokens.py
parac/compiler/__init__.py
parac/compiler/compiler.py
parac/compiler/ctx.py
parac/compiler/error_handler.py
parac/compiler/logic_stream.py
parac/compiler/logic_tokens.py
parac/compiler/process.py
parac/compiler/optimiser/__init__.py
parac/compiler/parser/__init__.py
parac/compiler/parser/listener.py
parac/compiler/parser/python/ParaCLexer.py
parac/compiler/parser/python/ParaCListener.py
parac/compiler/parser/python/ParaCParser.py
parac/compiler/parser/python/__init__.py
parac/preprocessor/__init__.py
parac/preprocessor/__main__.py
parac/preprocessor/ctx.py
parac/preprocessor/error_handler.py
parac/preprocessor/listener.py
parac/preprocessor/logic_stream.py
parac/preprocessor/logic_tokens.py
parac/preprocessor/abc/__init__.py
parac/preprocessor/abc/base_token.py
parac/preprocessor/python/ParaCPreProcessorLexer.py
parac/preprocessor/python/ParaCPreProcessorListener.py
parac/preprocessor/python/ParaCPreProcessorParser.py
parac/preprocessor/python/__init__.py
parac/util/__init__.py
parac/util/c_compiler.py
parac/util/cleanup_man.py
parac/util/decorators.py
parac/util/parser_ctx_tools.py
parac/util/pathtools.py
parac/util/stream.py
parac/util/strtools.py
parac-0.1.dev6.dist-info/LICENSE
parac-0.1.dev6.dist-info/METADATA
parac-0.1.dev6.dist-info/WHEEL
parac-0.1.dev6.dist-info/top_level.txt
parac-0.1.dev6.dist-info/RECORD
