Metadata-Version: 2.1
Name: parac
Version: 0.1.dev6
Summary: Python-Compiler for Para-C
Home-page: https://github.com/Luna-Klatzer/Para-C/
Author: Luna Klatzer
Author-email: luna.klatzer@gmail.com
Maintainer: Luna Klatzer
Maintainer-email: luna.klatzer@gmail.com
License: GNU GENERAL PUBLIC LICENSE v3.0
Project-URL: Issue-Page, https://github.com/Luna-Klatzer/Para-C/issues/
Project-URL: Changelog, https://github.com/Luna-Klatzer/Para-C/releases
Platform: UNKNOWN
Classifier: Development Status :: 2 - Pre-Alpha
Classifier: Programming Language :: Python :: 3
Classifier: Programming Language :: Python :: 3.8
Classifier: Programming Language :: Python :: 3.9
Classifier: Programming Language :: Python :: 3.10
Classifier: Programming Language :: C
Classifier: License :: OSI Approved :: GNU General Public License v3 (GPLv3)
Classifier: Environment :: Console
Classifier: Environment :: Other Environment
Classifier: Topic :: Software Development :: Code Generators
Classifier: Topic :: Software Development :: Compilers
Classifier: Intended Audience :: Developers
Classifier: Intended Audience :: Information Technology
Classifier: Operating System :: POSIX
Classifier: Operating System :: MacOS :: MacOS X
Classifier: Operating System :: Microsoft :: Windows
Requires-Python: >=3.8
License-File: LICENSE
Requires-Dist: colorama (>=0.4.4)
Requires-Dist: click (>=8.0.0)
Requires-Dist: setuptools (>=51.1.2)
Requires-Dist: rich (>=10.0.0)
Requires-Dist: antlr4-python3-runtime (>=4.9)
Requires-Dist: cached-property (>=1.5.1)
